{
  "version": "1",
  "cognitoConfig": {
    "identityPoolName": "testamplifyfigmab5c930b8_identitypool_b5c930b8",
    "allowUnauthenticatedIdentities": false,
    "resourceNameTruncated": "testamb5c930b8",
    "userPoolName": "testamplifyfigmab5c930b8_userpool_b5c930b8",
    "autoVerifiedAttributes": [
      "email"
    ],
    "mfaConfiguration": "OFF",
    "mfaTypes": [
      "SMS Text Message"
    ],
    "smsAuthenticationMessage": "Your authentication code is {####}",
    "smsVerificationMessage": "Your verification code is {####}",
    "emailVerificationSubject": "Your verification code",
    "emailVerificationMessage": "Your verification code is {####}",
    "defaultPasswordPolicy": false,
    "passwordPolicyMinLength": 8,
    "passwordPolicyCharacters": [],
    "requiredAttributes": [
      "email"
    ],
    "aliasAttributes": [],
    "userpoolClientGenerateSecret": false,
    "userpoolClientRefreshTokenValidity": 30,
    "userpoolClientWriteAttributes": [
      "email"
    ],
    "userpoolClientReadAttributes": [
      "email"
    ],
    "userpoolClientLambdaRole": "testamb5c930b8_userpoolclient_lambda_role",
    "userpoolClientSetAttributes": false,
    "sharedId": "b5c930b8",
    "resourceName": "testamplifyfigmab5c930b8",
    "authSelections": "identityPoolAndUserPool",
    "useDefault": "default",
    "userPoolGroupList": [],
    "serviceName": "Cognito",
    "usernameCaseSensitive": false,
    "useEnabledMfas": true
  }
}